<?xml version="1.0" encoding="UTF-8"?>
<odoo>
    <data>
        
        <!-- Vista Lista de Recepciones -->
        <record id="view_sample_reception_list" model="ir.ui.view">
            <field name="name">lims.sample.reception.list</field>
            <field name="model">lims.sample.reception</field>
            <field name="arch" type="xml">
                <list string="Recepciones de Muestras">
                    <field name="sample_code"/>
                    <field name="sample_identifier"/>
                    <field name="cliente_id"/>
                    <field name="reception_date"/>
                    <field name="reception_time"/>
                    <field name="reception_state"/>
                    <field name="received_by"/>
                </list>
            </field>
        </record>

        <!-- Vista Formulario de Recepci贸n SIMPLIFICADA -->
        <record id="view_sample_reception_form" model="ir.ui.view">
            <field name="name">lims.sample.reception.form</field>
            <field name="model">lims.sample.reception</field>
            <field name="arch" type="xml">
                <form string="Recepci贸n de Muestra">
                    <header>
                        <field name="reception_state" widget="statusbar" 
                            statusbar_visible="no_recibida,rechazada,recibida"/>               
                    </header>
                    
                    <sheet>
                        <div class="oe_title">
                            <h1>
                                <field name="sample_code" placeholder="Se genera autom谩ticamente"/>
                            </h1>
                        </div>

                        <!-- Informaci贸n b谩sica -->
                        <group>
                            <group string="И Informaci贸n de la Muestra">
                                <field name="sample_id" invisible="1"/>
                                <field name="sample_identifier" readonly="1"/>
                                <field name="custody_chain_id" readonly="1"/>
                                <field name="cliente_id" readonly="1"/>
                            </group>
                            <group string=" Datos de Recepci贸n">
                                <field name="reception_date"/>
                                <field name="reception_time" placeholder="14:30"/>
                                <field name="received_by"/>
                                <field name="received_by_initials"/>
                            </group>
                        </group>

                        <!-- Estado de recepci贸n -->
                        <group string=" Estado de Recepci贸n">
                            <field name="reception_state" widget="radio"/>
                        </group>

                        <!-- Par谩metros de la Muestra (solo lectura) -->
                        <group string=" Par谩metros de An谩lisis">
                            <field name="parameter_ids" nolabel="1" readonly="1">
                                <list string="Par谩metros">
                                    <field name="name"/>
                                    <field name="microorganism"/>
                                    <field name="method"/>
                                    <field name="category"/>
                                    <field name="unit"/>
                                </list>
                            </field>
                        </group>

                        <!-- Observaciones -->
                        <group string=" Observaciones">
                            <field name="reception_notes" nolabel="1" 
                                placeholder="Observaciones generales sobre la recepci贸n (visible para el cliente)..."/>
                        </group>

                        <group string=" Observaciones Internas">
                            <field name="internal_reception_notes" nolabel="1" 
                                placeholder="Notas internas del laboratorio (solo para uso interno)..."/>
                        </group>

                        <!-- Campos deprecados ocultos para compatibilidad -->
                        <group string="Campos de Compatibilidad" invisible="1">
                            <field name="check_conditions" invisible="1"/>
                            <field name="check_temperature" invisible="1"/>
                            <field name="check_container" invisible="1"/>
                            <field name="check_volume" invisible="1"/>
                            <field name="check_preservation" invisible="1"/>
                            <field name="can_change_state" invisible="1"/>
                            <field name="conditions_notes" invisible="1"/>
                            <field name="temperature_notes" invisible="1"/>
                            <field name="container_notes" invisible="1"/>
                            <field name="volume_notes" invisible="1"/>
                            <field name="preservation_notes" invisible="1"/>
                            <field name="can_process_conditions" invisible="1"/>
                            <field name="can_process_temperature" invisible="1"/>
                            <field name="can_process_container" invisible="1"/>
                            <field name="can_process_volume" invisible="1"/>
                            <field name="can_process_preservation" invisible="1"/>
                        </group>

                    </sheet>
                </form>
            </field>
        </record>

        <!-- Acci贸n principal -->
        <record id="action_sample_receptions" model="ir.actions.act_window">
            <field name="name">Recepciones de Muestras</field>
            <field name="res_model">lims.sample.reception</field>
            <field name="view_mode">list,form</field>
            <field name="help" type="html">
                <p class="o_view_nocontent_smiling_face">
                    No hay recepciones registradas
                </p>
                <p>
                    Las recepciones se crean desde las cadenas de custodia
                </p>
            </field>
        </record>

    </data>
</odoo>